src/vrsget/monitorFunctions.py
src/vrsget/search.py
vrsget-0.1.dist-info/METADATA
vrsget-0.1.dist-info/WHEEL
vrsget-0.1.dist-info/licenses/LICENSE
vrsget-0.1.dist-info/RECORD
